{
  "liblabVersion": "2.1.28",
  "date": "2024-08-21T11:02:22.586Z",
  "config": {
    "apiId": 947,
    "sdkName": "signplus",
    "sdkVersion": "1.0.0",
    "liblabVersion": "2",
    "deliveryMethods": ["zip"],
    "languages": ["typescript"],
    "apiVersion": "2.0.0",
    "apiName": "signplus-api",
    "specFilePath": "openapi.yaml",
    "auth": ["bearer"],
    "languageOptions": {
      "csharp": {
        "packageId": "Alohi.Signplus",
        "githubRepoName": "signplus-sharp",
        "ignoreFiles": [],
        "liblabVersion": "2",
        "sdkVersion": "1.0.0"
      },
      "go": {
        "goModuleName": "github.com/alohihq/signplus-go",
        "additionalConstructorParameters": [],
        "githubRepoName": "signplus-go",
        "ignoreFiles": [],
        "liblabVersion": "2",
        "sdkVersion": "1.0.0"
      },
      "java": {
        "groupId": "alohi.signplus",
        "additionalConstructorParameters": [],
        "githubRepoName": "signplus-java",
        "liblabVersion": "2",
        "sdkVersion": "1.0.0"
      },
      "python": {
        "alwaysInitializeOptionals": false,
        "additionalConstructorParameters": [],
        "pypiPackageName": "signplus-python",
        "githubRepoName": "signplus-python",
        "ignoreFiles": [],
        "liblabVersion": "2",
        "sdkVersion": "1.0.0"
      },
      "php": {
        "packageName": "alohi/signplus",
        "additionalConstructorParameters": [],
        "githubRepoName": "signplus-php",
        "ignoreFiles": [],
        "liblabVersion": "2",
        "sdkVersion": "2.0.0"
      },
      "typescript": {
        "bundle": false,
        "exportClassDefault": false,
        "httpClient": "axios",
        "npmName": "signplus-typescript",
        "npmOrg": "alohi",
        "additionalConstructorParameters": [],
        "githubRepoName": "signplus-typescript",
        "ignoreFiles": [],
        "liblabVersion": "2",
        "sdkVersion": "1.0.0"
      }
    },
    "publishing": {
      "githubOrg": "alohihq"
    },
    "authentication": {
      "access": {
        "prefix": "Bearer"
      }
    },
    "devContainer": false,
    "generateEnv": true,
    "includeOptionalSnippetParameters": true,
    "inferServiceNames": false,
    "injectedModels": [],
    "license": {
      "type": "MIT",
      "name": "MIT",
      "url": "https://opensource.org/licenses/MIT",
      "path": "MIT.ejs"
    },
    "responseHeaders": false,
    "retry": {
      "enabled": true,
      "maxAttempts": 3,
      "retryDelay": 150,
      "maxDelay": 5000,
      "retryDelayJitter": 50,
      "backOffFactor": 2,
      "httpCodesToRetry": [408, 429, 500, 502, 503, 504],
      "httpMethodsToRetry": ["GET", "POST", "PUT", "DELETE", "PATCH", "HEAD", "OPTIONS"]
    },
    "multiTenant": true,
    "specUrl": "https://prod-liblab-api-stack-specs.s3.us-east-1.amazonaws.com/947/open-api-spec.yaml?X-Amz-Algorithm=AWS4-HMAC-SHA256&X-Amz-Content-Sha256=UNSIGNED-PAYLOAD&X-Amz-Credential=AKIA5P3QKKDKGVNIJ2H7%2F20240821%2Fus-east-1%2Fs3%2Faws4_request&X-Amz-Date=20240821T110214Z&X-Amz-Expires=43200&X-Amz-Signature=009d5622184bfe1c39e60a5d0a55af4a2e741c467ac7da365003bdd60373a218&X-Amz-SignedHeaders=host&x-id=GetObject",
    "includeWatermark": false,
    "language": "typescript",
    "deliveryMethod": "zip",
    "hooks": {
      "enabled": false,
      "sourceDir": ""
    },
    "bundle": false,
    "exportClassDefault": false,
    "httpClient": "axios",
    "npmName": "signplus-typescript",
    "npmOrg": "alohi",
    "additionalConstructorParameters": [],
    "githubRepoName": "signplus-typescript",
    "ignoreFiles": [],
    "typescriptVersion": "5.3.3",
    "zodVersion": "3.22.0",
    "compilerOptions": {
      "target": "es6",
      "module": "Node16",
      "lib": ["es2017", "dom"]
    },
    "usesFormData": false,
    "environmentVariables": [],
    "fileOutput": "/tmp",
    "httpLibrary": {
      "name": "axios",
      "packages": {
        "axios": "^1.7.4"
      },
      "languages": ["typescript"]
    },
    "customQueries": {
      "paths": [],
      "rawQueries": [],
      "queriesData": []
    }
  },
  "files": [
    "package.json",
    "tsconfig.json",
    "examples/tsconfig.json",
    "examples/package.json",
    "examples/README.md",
    "examples/src/index.ts",
    "src/http/client.ts",
    "src/services/signplus/models/create-envelope-request.ts",
    "src/services/signplus/models/envelope.ts",
    "src/services/signplus/models/create-envelope-from-template-request.ts",
    "src/services/signplus/models/list-envelopes-request.ts",
    "src/services/signplus/models/list-envelopes-response.ts",
    "src/services/signplus/models/document.ts",
    "src/services/signplus/models/list-envelope-documents-response.ts",
    "src/services/signplus/models/add-envelope-document-request.ts",
    "src/services/signplus/models/set-envelope-dynamic-fields-request.ts",
    "src/services/signplus/models/add-envelope-signing-steps-request.ts",
    "src/services/signplus/models/rename-envelope-request.ts",
    "src/services/signplus/models/set-envelope-comment-request.ts",
    "src/services/signplus/models/envelope-notification.ts",
    "src/services/signplus/models/set-envelope-expiration-request.ts",
    "src/services/signplus/models/set-envelope-legality-level-request.ts",
    "src/services/signplus/models/annotation.ts",
    "src/services/signplus/models/list-envelope-document-annotations-response.ts",
    "src/services/signplus/models/add-annotation-request.ts",
    "src/services/signplus/models/create-template-request.ts",
    "src/services/signplus/models/template.ts",
    "src/services/signplus/models/list-templates-request.ts",
    "src/services/signplus/models/list-templates-response.ts",
    "src/services/signplus/models/add-template-document-request.ts",
    "src/services/signplus/models/list-template-documents-response.ts",
    "src/services/signplus/models/add-template-signing-steps-request.ts",
    "src/services/signplus/models/rename-template-request.ts",
    "src/services/signplus/models/set-template-comment-request.ts",
    "src/services/signplus/models/list-template-annotations-response.ts",
    "src/services/signplus/models/list-template-document-annotations-response.ts",
    "src/services/signplus/models/create-webhook-request.ts",
    "src/services/signplus/models/webhook.ts",
    "src/services/signplus/models/list-webhooks-request.ts",
    "src/services/signplus/models/list-webhooks-response.ts",
    "src/services/signplus/models/envelope-legality-level.ts",
    "src/services/signplus/models/envelope-flow-type.ts",
    "src/services/signplus/models/envelope-status.ts",
    "src/services/signplus/models/signing-step.ts",
    "src/services/signplus/models/recipient.ts",
    "src/services/signplus/models/recipient-role.ts",
    "src/services/signplus/models/recipient-verification.ts",
    "src/services/signplus/models/recipient-verification-type.ts",
    "src/services/signplus/models/page.ts",
    "src/services/signplus/models/envelope-order-field.ts",
    "src/services/signplus/models/dynamic-field.ts",
    "src/services/signplus/models/annotation-type.ts",
    "src/services/signplus/models/annotation-signature.ts",
    "src/services/signplus/models/annotation-initials.ts",
    "src/services/signplus/models/annotation-text.ts",
    "src/services/signplus/models/annotation-date-time.ts",
    "src/services/signplus/models/annotation-checkbox.ts",
    "src/services/signplus/models/annotation-font.ts",
    "src/services/signplus/models/annotation-font-family.ts",
    "src/services/signplus/models/annotation-date-time-format.ts",
    "src/services/signplus/models/annotation-checkbox-style.ts",
    "src/services/signplus/models/template-signing-step.ts",
    "src/services/signplus/models/template-recipient.ts",
    "src/services/signplus/models/template-recipient-role.ts",
    "src/services/signplus/models/template-order-field.ts",
    "src/services/signplus/models/webhook-event.ts",
    ".gitignore",
    "src/services/base-service.ts",
    "src/services/signplus/signplus.ts",
    "src/index.ts",
    "src/services/signplus/models/index.ts",
    "src/services/signplus/index.ts",
    "src/http/index.ts",
    "src/http/handlers/handler-chain.ts",
    "src/http/types.ts",
    "src/http/error.ts",
    "src/http/handlers/terminating-handler.ts",
    "src/http/handlers/hook-handler.ts",
    "src/http/hooks/custom-hook.ts",
    "src/http/hooks/hook.ts",
    "src/http/handlers/retry-handler.ts",
    "src/http/environment.ts",
    "src/http/handlers/response-validation-handler.ts",
    "src/http/handlers/auth-handler.ts",
    "./LICENSE",
    "documentation/models/CreateEnvelopeRequest.md",
    "documentation/models/Envelope.md",
    "documentation/models/CreateEnvelopeFromTemplateRequest.md",
    "documentation/models/ListEnvelopesRequest.md",
    "documentation/models/ListEnvelopesResponse.md",
    "documentation/models/Document.md",
    "documentation/models/ListEnvelopeDocumentsResponse.md",
    "documentation/models/AddEnvelopeDocumentRequest.md",
    "documentation/models/SetEnvelopeDynamicFieldsRequest.md",
    "documentation/models/AddEnvelopeSigningStepsRequest.md",
    "documentation/models/RenameEnvelopeRequest.md",
    "documentation/models/SetEnvelopeCommentRequest.md",
    "documentation/models/EnvelopeNotification.md",
    "documentation/models/SetEnvelopeExpirationRequest.md",
    "documentation/models/SetEnvelopeLegalityLevelRequest.md",
    "documentation/models/Annotation.md",
    "documentation/models/ListEnvelopeDocumentAnnotationsResponse.md",
    "documentation/models/AddAnnotationRequest.md",
    "documentation/models/CreateTemplateRequest.md",
    "documentation/models/Template.md",
    "documentation/models/ListTemplatesRequest.md",
    "documentation/models/ListTemplatesResponse.md",
    "documentation/models/AddTemplateDocumentRequest.md",
    "documentation/models/ListTemplateDocumentsResponse.md",
    "documentation/models/AddTemplateSigningStepsRequest.md",
    "documentation/models/RenameTemplateRequest.md",
    "documentation/models/SetTemplateCommentRequest.md",
    "documentation/models/ListTemplateAnnotationsResponse.md",
    "documentation/models/ListTemplateDocumentAnnotationsResponse.md",
    "documentation/models/CreateWebhookRequest.md",
    "documentation/models/Webhook.md",
    "documentation/models/ListWebhooksRequest.md",
    "documentation/models/ListWebhooksResponse.md",
    "documentation/models/EnvelopeLegalityLevel.md",
    "documentation/models/EnvelopeFlowType.md",
    "documentation/models/EnvelopeStatus.md",
    "documentation/models/SigningStep.md",
    "documentation/models/Recipient.md",
    "documentation/models/RecipientRole.md",
    "documentation/models/RecipientVerification.md",
    "documentation/models/RecipientVerificationType.md",
    "documentation/models/Page.md",
    "documentation/models/EnvelopeOrderField.md",
    "documentation/models/DynamicField.md",
    "documentation/models/AnnotationType.md",
    "documentation/models/AnnotationSignature.md",
    "documentation/models/AnnotationInitials.md",
    "documentation/models/AnnotationText.md",
    "documentation/models/AnnotationDateTime.md",
    "documentation/models/AnnotationCheckbox.md",
    "documentation/models/AnnotationFont.md",
    "documentation/models/AnnotationFontFamily.md",
    "documentation/models/AnnotationDateTimeFormat.md",
    "documentation/models/AnnotationCheckboxStyle.md",
    "documentation/models/TemplateSigningStep.md",
    "documentation/models/TemplateRecipient.md",
    "documentation/models/TemplateRecipientRole.md",
    "documentation/models/TemplateOrderField.md",
    "documentation/models/WebhookEvent.md",
    "src/http/handlers/request-validation-handler.ts",
    "src/http/transport/request.ts",
    "src/http/transport/request-builder.ts",
    "src/http/serialization/base-serializer.ts",
    "src/http/serialization/query-serializer.ts",
    "src/http/serialization/path-serializer.ts",
    "src/http/serialization/header-serializer.ts",
    "src/http/transport/request-fetch-adapter.ts",
    "src/http/transport/transport-hook-adapter.ts",
    "README.md",
    "documentation/services/SignplusService.md"
  ]
}
